[
	{
		"symbol": "SMPL",
		"name": "Sample",
		"lastTradePrice": 10,
		"changePrice": 2.4,
		"changePercent": "0.5%",
		"marketCap": "23.4M",
		"openPrice": 9.5,
		"highPrice": 12,
		"lowPrice": 9.3,
		"volume": "25.6M",
		"avgVolume": "42.3M",
		"peRatio": 6.2,
		"wkHigh": 15,
		"wkLow": 9,
		"yield": 2.3
	},
	{
		"symbol": "AAPL",
		"name": "Apple Inc.",
		"lastTradePrice": 419.11,
		"changePrice": -0.88,
		"changePercent": "-0.21%",
		"marketCap": "388.6B",
		"openPrice": 421.59,
		"highPrice": 422.30,
		"lowPrice": 417.34,
		"volume": "3.27M",
		"avgVolume": "22.97M",
		"peRatio": 16.62,
		"wkHigh": 422.86,
		"wkLow": 277.77,
		"yield": "&mdash;"
	},
	{
		"symbol": "T",
		"name": "AT&T Inc.",
		"lastTradePrice": 29.07,
		"changePrice": -0.10,
		"changePercent": "-0.34%",
		"marketCap": "172.3B",
		"openPrice": 29.19,
		"highPrice": 29.38,
		"lowPrice": 28.93,
		"volume": "99.8M",
		"avgVolume": "348.16M",
		"peRatio": 8.49,
		"wkHigh": 31.94,
		"wkLow": 27.20,
		"yield": 5.86
	},
	{
		"symbol": "^DJI",
		"name": "Dow Jones Industrial Average",
		"lastTradePrice": 11396.81,
		"changePrice": -247.68,
		"changePercent": "-2.13%",
		"marketCap": "&mdash;",
		"openPrice": 11643.35,
		"highPrice": 11643.35,
		"lowPrice": 11388.90,
		"volume": "73.82M",
		"avgVolume": "&mdash;",
		"peRatio": "&mdash;",
		"wkHigh": 12876,
		"wkLow": 10404.49,
		"yield": "&mdash;"
	},
	{
		"symbol": "EK",
		"name": "Eastman Kodak Company",
		"lastTradePrice": 1.28,
		"changePrice": 0.04,
		"changePercent": "3.23%",
		"marketCap": "344.4M",
		"openPrice": 1.39,
		"highPrice": 1.39,
		"lowPrice": 1.26,
		"volume": "5.96M",
		"avgVolume": "16.09M",
		"peRatio": "&mdash;",
		"wkHigh": 5.95,
		"wkLow": 0.54,
		"yield": "&mdash;"
	}
]